devfixtures/__init__.py
devfixtures/apps.py
devfixtures/management/__init__.py
devfixtures/management/commands/__init__.py
devfixtures/management/commands/devfixture.py
django_devfixtures-0.1.3.dist-info/DESCRIPTION.rst
django_devfixtures-0.1.3.dist-info/METADATA
django_devfixtures-0.1.3.dist-info/RECORD
django_devfixtures-0.1.3.dist-info/WHEEL
django_devfixtures-0.1.3.dist-info/metadata.json
django_devfixtures-0.1.3.dist-info/top_level.txt
